infrahouse_toolkit/__init__.py
infrahouse_toolkit/exceptions.py
infrahouse_toolkit/fs.py
infrahouse_toolkit/timeout.py
infrahouse_toolkit/aws/__init__.py
infrahouse_toolkit/aws/asg.py
infrahouse_toolkit/aws/asg_instance.py
infrahouse_toolkit/aws/config.py
infrahouse_toolkit/aws/ec2_instance.py
infrahouse_toolkit/aws/exceptions.py
infrahouse_toolkit/aws/tests/__init__.py
infrahouse_toolkit/aws/tests/config/__init__.py
infrahouse_toolkit/aws/tests/config/test_aws_home.py
infrahouse_toolkit/aws/tests/config/test_get_account_id.py
infrahouse_toolkit/aws/tests/config/test_get_region.py
infrahouse_toolkit/aws/tests/config/test_get_sso_region.py
infrahouse_toolkit/aws/tests/config/test_profiles.py
infrahouse_toolkit/cli/__init__.py
infrahouse_toolkit/cli/exceptions.py
infrahouse_toolkit/cli/gpg.py
infrahouse_toolkit/cli/lib.py
infrahouse_toolkit/cli/utils.py
infrahouse_toolkit/cli/ih_aws/__init__.py
infrahouse_toolkit/cli/ih_aws/cmd_autoscaling/__init__.py
infrahouse_toolkit/cli/ih_aws/cmd_autoscaling/cmd_complete/__init__.py
infrahouse_toolkit/cli/ih_aws/cmd_autoscaling/cmd_mark_unhealthy/__init__.py
infrahouse_toolkit/cli/ih_aws/cmd_autoscaling/cmd_scale_in/__init__.py
infrahouse_toolkit/cli/ih_aws/cmd_credentials/__init__.py
infrahouse_toolkit/cli/ih_aws/cmd_ecs/__init__.py
infrahouse_toolkit/cli/ih_aws/cmd_ecs/cmd_wait_services_stable/__init__.py
infrahouse_toolkit/cli/ih_certbot/__init__.py
infrahouse_toolkit/cli/ih_ec2/__init__.py
infrahouse_toolkit/cli/ih_ec2/cmd_instance_types/__init__.py
infrahouse_toolkit/cli/ih_ec2/cmd_launch/__init__.py
infrahouse_toolkit/cli/ih_ec2/cmd_launch_templates/__init__.py
infrahouse_toolkit/cli/ih_ec2/cmd_list/__init__.py
infrahouse_toolkit/cli/ih_ec2/cmd_subnets/__init__.py
infrahouse_toolkit/cli/ih_ec2/cmd_tags/__init__.py
infrahouse_toolkit/cli/ih_ec2/cmd_terminate/__init__.py
infrahouse_toolkit/cli/ih_elastic/__init__.py
infrahouse_toolkit/cli/ih_elastic/cmd_api.py
infrahouse_toolkit/cli/ih_elastic/cmd_cat/__init__.py
infrahouse_toolkit-2.56.0.dist-info/licenses/AUTHORS.rst
infrahouse_toolkit-2.56.0.dist-info/licenses/LICENSE
infrahouse_toolkit-2.56.0.dist-info/METADATA
infrahouse_toolkit-2.56.0.dist-info/WHEEL
infrahouse_toolkit-2.56.0.dist-info/entry_points.txt
infrahouse_toolkit-2.56.0.dist-info/top_level.txt
infrahouse_toolkit-2.56.0.dist-info/RECORD
