Metadata-Version: 2.4
Name: infrahouse-toolkit
Version: 2.56.0
Summary: A collection of tools for building infrastructure.
Home-page: https://github.com/infrahouse/infrahouse-toolkit
Author: Oleksandr Kuzminskyi
Author-email: aleks@infrahouse.com
License: Apache Software License 2.0
Keywords: infrahouse-toolkit
Classifier: Development Status :: 2 - Pre-Alpha
Classifier: Intended Audience :: Developers
Classifier: License :: OSI Approved :: Apache Software License
Classifier: Natural Language :: English
Classifier: Programming Language :: Python :: 3
Classifier: Programming Language :: Python :: 3.8
Classifier: Programming Language :: Python :: 3.9
Classifier: Programming Language :: Python :: 3.10
Requires-Python: >=3.8
License-File: LICENSE
License-File: AUTHORS.rst
Requires-Dist: boto3~=1.26
Requires-Dist: botocore~=1.29
Requires-Dist: cached-property~=2.0
Requires-Dist: certbot~=4.1
Requires-Dist: certbot-dns-route53~=4.1
Requires-Dist: click~=8.1
Requires-Dist: cryptography>=45.0.4,~=45.0
Requires-Dist: diskcache~=5.6
Requires-Dist: ec2-metadata~=2.13
Requires-Dist: elastic-transport~=8.12.0
Requires-Dist: elasticsearch~=8.12.0
Requires-Dist: GitPython>=3.1.30,~=3.1
Requires-Dist: infrahouse-core~=0.19
Requires-Dist: PyGithub~=2.4
Requires-Dist: pyhcl~=0.4
Requires-Dist: pyjwt~=2.9
Requires-Dist: requests>=2.32.4,~=2.32
Requires-Dist: tabulate~=0.9
Requires-Dist: wcwidth~=0.2
Dynamic: author
Dynamic: author-email
Dynamic: classifier
Dynamic: description
Dynamic: home-page
Dynamic: keywords
Dynamic: license
Dynamic: license-file
Dynamic: requires-dist
Dynamic: requires-python
Dynamic: summary
